deltapv/__init__.py
deltapv/adjoint.py
deltapv/bcond.py
deltapv/current.py
deltapv/dataclasses_dpv.py
deltapv/ddiff.py
deltapv/linalg.py
deltapv/materials.py
deltapv/objects.py
deltapv/optical.py
deltapv/physics.py
deltapv/plotting.py
deltapv/poisson.py
deltapv/recomb.py
deltapv/residual.py
deltapv/scales.py
deltapv/simulator.py
deltapv/solver.py
deltapv/spline.py
deltapv/sun.py
deltapv/util.py
deltapv/fonts/cmunbx.ttf
deltapv/fonts/cmunrm.ttf
deltapv/fonts/cmunti.ttf
deltapv/resources/AlN.csv
deltapv/resources/AlN.yaml
deltapv/resources/BN.yaml
deltapv/resources/GaAs.csv
deltapv/resources/GaAs.yaml
deltapv/resources/GaN.yaml
deltapv/resources/GaP.csv
deltapv/resources/GaP.yaml
deltapv/resources/GaSb.yaml
deltapv/resources/Ge.csv
deltapv/resources/Ge.yaml
deltapv/resources/InAs.yaml
deltapv/resources/InN.yaml
deltapv/resources/InP.csv
deltapv/resources/InP.yaml
deltapv/resources/InSb.yaml
deltapv/resources/Si.csv
deltapv/resources/Si.yaml
deltapv-0.0.5.dist-info/licenses/LICENSE
deltapv-0.0.5.dist-info/METADATA
deltapv-0.0.5.dist-info/WHEEL
deltapv-0.0.5.dist-info/top_level.txt
deltapv-0.0.5.dist-info/RECORD
