Metadata-Version: 2.4
Name: deltapv
Version: 0.0.5
Summary: Solar cell simulator with automatic differentiation
Author: Sean Mann, Eric Richard Fadel, Ekin Dogus Cubuk, Sam Schoenholz, and Giuseppe Romano
License: MIT
Classifier: Programming Language :: Python :: 3.7
License-File: LICENSE
Requires-Dist: numpy
Requires-Dist: jax
Requires-Dist: jaxlib
Requires-Dist: matplotlib
Requires-Dist: pandas
Requires-Dist: equinox
Requires-Dist: pyyaml
Requires-Dist: scipy
Dynamic: author
Dynamic: classifier
Dynamic: description
Dynamic: description-content-type
Dynamic: license
Dynamic: license-file
Dynamic: requires-dist
Dynamic: summary
